{
	"$schema": "https://schema.management.azure.com/schemas/2015-01-01/deploymentParameters.json#",
	"contentVersion": "1.0.0.0",
	"parameters": {
		"workspaceName": {
			"value": "workspacesynapsepublics"
		},
		"workspacesynapsepublics-WorkspaceDefaultSqlServer_connectionString": {
			"value": "Integrated Security=False;Encrypt=True;Connection Timeout=30;Data Source=tcp:workspacesynapsepublics.sql.azuresynapse.net,1433;Initial Catalog=@{linkedService().DBName}"
		},
		"workspacesynapsepublics-WorkspaceDefaultStorage_properties_typeProperties_url": {
			"value": "https://datalakesynapsepublics.dfs.core.windows.net"
		}
	}
}